Metadata-Version: 2.1
Name: time-spread
Version: 0.0.1
Summary: Simple Python CLI for printing time in multiple time zones.
Author-email: Matt Rhoads <mrhoads1@gmail.com>
License: MIT License
Project-URL: Homepage, https://github.com/rckwzrd/time-spread
Keywords: time,cli
Classifier: Programming Language :: Python :: 3
Requires-Python: >=3.8
License-File: LICENSE.txt
Requires-Dist: arrow
Requires-Dist: click
Provides-Extra: dev
Requires-Dist: build ; extra == 'dev'
Requires-Dist: pytest ; extra == 'dev'
Requires-Dist: twine ; extra == 'dev'
